{"status":true,"message":"Test data","data":{"layer":"3","list":[{"test_series_type":"1","closing_date":"0","first_attempt":null,"attempt_limit":"0","id":"251713","mode":"0","price":"0","is_gst":"0","tax_rate":"0","result_date":"0","image":"","test_series_name":"Carbon and its Compound","title":"Carbon and its Compound","test_code":"10th Science Carbon and its Compound ","test_type":"0","set_type":"0","total_marks":"50","start_date":"1760170698","end_date":"1924321666","lang_id":"1","type":"test","day_wise":"0","is_locked":"1","total_questions":"10","time_in_mins":"30","is_reattempt":"0","report_id":"0","marks":"2","state":"","correct_count":"0","incorrect_count":"0","lang_used":"","submission_type":"0","result_status":"NA","description":"","solutions":"","question":"","answers":"","attempt":"0","answers_by_student":"","test_pattern":"0","folder_id":"0","l1_id":"8615","upload_allowed":"1","file_type":"t","is_test_purchased":"0","payload":{"topic_id":"35850","tile_id":"93496","tile_type":"test","revert_api":"0#0#0#0","course_id":"29246","day_wise":"0"}},{"test_series_type":"0","closing_date":"0","first_attempt":null,"attempt_limit":"0","id":"250779","mode":"0","price":"0","is_gst":"0","tax_rate":"0","result_date":"0","image":"","test_series_name":"Magnetic Effect of Electric Current","title":"Magnetic Effect of Electric Current","test_code":"Magnetic Effect of Electric Current  10th ","test_type":"0","set_type":"0","total_marks":"20","start_date":"1758715200","end_date":"1785931020","lang_id":"1","type":"test","day_wise":"0","is_locked":"1","total_questions":"10","time_in_mins":"25","is_reattempt":"1781006220","report_id":"0","marks":"2","state":"","correct_count":"0","incorrect_count":"0","lang_used":"","submission_type":"0","result_status":"NA","description":"","solutions":"","question":"","answers":"","attempt":"0","answers_by_student":"","test_pattern":"0","folder_id":"0","l1_id":"8615","upload_allowed":"1","file_type":"t","is_test_purchased":"0","payload":{"topic_id":"35850","tile_id":"93496","tile_type":"test","revert_api":"0#0#0#0","course_id":"29246","day_wise":"0"}},{"test_series_type":"1","closing_date":"0","first_attempt":null,"attempt_limit":"0","id":"250141","mode":"0","price":"0","is_gst":"0","tax_rate":"0","result_date":"0","image":"","test_series_name":"How Do organisms Reproduce ?","title":"How Do organisms Reproduce ?","test_code":"005","test_type":"0","set_type":"0","total_marks":"50","start_date":"1757858585","end_date":"1924321666","lang_id":"1","type":"test","day_wise":"0","is_locked":"1","total_questions":"10","time_in_mins":"30","is_reattempt":"0","report_id":"0","marks":"2","state":"","correct_count":"0","incorrect_count":"0","lang_used":"","submission_type":"0","result_status":"NA","description":"","solutions":"","question":"","answers":"","attempt":"0","answers_by_student":"","test_pattern":"0","folder_id":"0","l1_id":"8615","upload_allowed":"1","file_type":"t","is_test_purchased":"0","payload":{"topic_id":"35850","tile_id":"93496","tile_type":"test","revert_api":"0#0#0#0","course_id":"29246","day_wise":"0"}},{"test_series_type":"0","closing_date":"0","first_attempt":null,"attempt_limit":"0","id":"246743","mode":"0","price":"0","is_gst":"0","tax_rate":"0","result_date":"0","image":"","test_series_name":"Electricity","title":"Electricity","test_code":"Electricity ","test_type":"0","set_type":"0","total_marks":"75","start_date":"1756134240","end_date":"1785510120","lang_id":"1","type":"test","day_wise":"0","is_locked":"1","total_questions":"15","time_in_mins":"30","is_reattempt":"1782313320","report_id":"0","marks":"2","state":"","correct_count":"0","incorrect_count":"0","lang_used":"","submission_type":"0","result_status":"NA","description":"","solutions":"","question":"","answers":"","attempt":"0","answers_by_student":"","test_pattern":"0","folder_id":"0","l1_id":"8615","upload_allowed":"1","file_type":"t","is_test_purchased":"0","payload":{"topic_id":"35850","tile_id":"93496","tile_type":"test","revert_api":"0#0#0#0","course_id":"29246","day_wise":"0"}},{"test_series_type":"0","closing_date":"0","first_attempt":null,"attempt_limit":"0","id":"245174","mode":"0","price":"0","is_gst":"0","tax_rate":"0","result_date":"0","image":"","test_series_name":"Metals and Non Metals","title":"Metals and Non Metals","test_code":"Metals and Non Metals 10th ","test_type":"0","set_type":"0","total_marks":"75","start_date":"1754214120","end_date":"1785577200","lang_id":"1","type":"test","day_wise":"0","is_locked":"1","total_questions":"15","time_in_mins":"30","is_reattempt":"1782898800","report_id":"0","marks":"2","state":"","correct_count":"0","incorrect_count":"0","lang_used":"","submission_type":"0","result_status":"NA","description":"","solutions":"","question":"","answers":"","attempt":"0","answers_by_student":"","test_pattern":"0","folder_id":"0","l1_id":"8615","upload_allowed":"1","file_type":"t","is_test_purchased":"0","payload":{"topic_id":"35850","tile_id":"93496","tile_type":"test","revert_api":"0#0#0#0","course_id":"29246","day_wise":"0"}},{"test_series_type":"0","closing_date":"0","first_attempt":null,"attempt_limit":"0","id":"243759","mode":"0","price":"0","is_gst":"0","tax_rate":"0","result_date":"0","image":"","test_series_name":"Control and coordination","title":"Control and coordination","test_code":"control and coordination class 10","test_type":"0","set_type":"0","total_marks":"75","start_date":"1753014300","end_date":"1785586980","lang_id":"1","type":"test","day_wise":"0","is_locked":"1","total_questions":"15","time_in_mins":"30","is_reattempt":"1780316580","report_id":"0","marks":"2","state":"","correct_count":"0","incorrect_count":"0","lang_used":"","submission_type":"0","result_status":"NA","description":"","solutions":"","question":"","answers":"","attempt":"0","answers_by_student":"","test_pattern":"0","folder_id":"0","l1_id":"8615","upload_allowed":"1","file_type":"t","is_test_purchased":"0","payload":{"topic_id":"35850","tile_id":"93496","tile_type":"test","revert_api":"0#0#0#0","course_id":"29246","day_wise":"0"}},{"test_series_type":"0","closing_date":"0","first_attempt":null,"attempt_limit":"0","id":"242327","mode":"0","price":"0","is_gst":"0","tax_rate":"0","result_date":"0","image":"","test_series_name":"tHuman eye and colourful world","title":"tHuman eye and colourful world","test_code":"class 10 test human eye and colourful world","test_type":"0","set_type":"0","total_marks":"75","start_date":"1752582360","end_date":"1785846240","lang_id":"1","type":"test","day_wise":"0","is_locked":"1","total_questions":"15","time_in_mins":"30","is_reattempt":"1784636640","report_id":"0","marks":"2","state":"","correct_count":"0","incorrect_count":"0","lang_used":"","submission_type":"0","result_status":"NA","description":"","solutions":"","question":"","answers":"","attempt":"0","answers_by_student":"","test_pattern":"0","folder_id":"0","l1_id":"8615","upload_allowed":"1","file_type":"t","is_test_purchased":"0","payload":{"topic_id":"35850","tile_id":"93496","tile_type":"test","revert_api":"0#0#0#0","course_id":"29246","day_wise":"0"}},{"test_series_type":"0","closing_date":"0","first_attempt":null,"attempt_limit":"1","id":"237964","mode":"0","price":"0","is_gst":"0","tax_rate":"0","result_date":"0","image":"","test_series_name":"Acid Bases and Salt","title":"Acid Bases and Salt","test_code":"Test acid bases and salt class 10","test_type":"0","set_type":"0","total_marks":"75","start_date":"1750524120","end_date":"1781714340","lang_id":"1","type":"test","day_wise":"0","is_locked":"1","total_questions":"15","time_in_mins":"30","is_reattempt":"1771951140","report_id":"0","marks":"2","state":"","correct_count":"0","incorrect_count":"0","lang_used":"","submission_type":"0","result_status":"NA","description":"","solutions":"","question":"","answers":"","attempt":"0","answers_by_student":"","test_pattern":"0","folder_id":"0","l1_id":"8615","upload_allowed":"1","file_type":"t","is_test_purchased":"0","payload":{"topic_id":"35850","tile_id":"93496","tile_type":"test","revert_api":"0#0#0#0","course_id":"29246","day_wise":"0"}},{"test_series_type":"0","closing_date":"0","first_attempt":null,"attempt_limit":"1","id":"237391","mode":"0","price":"0","is_gst":"0","tax_rate":"0","result_date":"0","image":"","test_series_name":"Life process","title":"Life process","test_code":"Test life process class 10","test_type":"0","set_type":"0","total_marks":"75","start_date":"1749975600","end_date":"1780387860","lang_id":"1","type":"test","day_wise":"0","is_locked":"1","total_questions":"15","time_in_mins":"30","is_reattempt":"1762342320","report_id":"0","marks":"2","state":"","correct_count":"0","incorrect_count":"0","lang_used":"","submission_type":"0","result_status":"NA","description":"","solutions":"","question":"","answers":"","attempt":"0","answers_by_student":"","test_pattern":"0","folder_id":"0","l1_id":"8615","upload_allowed":"1","file_type":"t","is_test_purchased":"0","payload":{"topic_id":"35850","tile_id":"93496","tile_type":"test","revert_api":"0#0#0#0","course_id":"29246","day_wise":"0"}},{"test_series_type":"0","closing_date":"0","first_attempt":"1","attempt_limit":"0","id":"229993","mode":"0","price":"0","is_gst":"0","tax_rate":"0","result_date":"0","image":"","test_series_name":"Light","title":"Light","test_code":"Light test aarambh 25-26","test_type":"0","set_type":"0","total_marks":"70","start_date":"1747665960","end_date":"1775054460","lang_id":"1","type":"test","day_wise":"0","is_locked":"1","total_questions":"14","time_in_mins":"30","is_reattempt":"1772376120","report_id":"9705088","marks":"5","state":"1","correct_count":"1","incorrect_count":"0","lang_used":"1","submission_type":"0","result_status":"NA","description":"","solutions":"","question":"","answers":"","attempt":"0","answers_by_student":"","test_pattern":"0","folder_id":"0","l1_id":"8615","upload_allowed":"1","file_type":"t","is_test_purchased":"0","payload":{"topic_id":"35850","tile_id":"93496","tile_type":"test","revert_api":"0#0#0#0","course_id":"29246","day_wise":"0"}},{"test_series_type":"0","closing_date":"0","first_attempt":"1","attempt_limit":"0","id":"204217","mode":"0","price":"0","is_gst":"0","tax_rate":"0","result_date":"0","image":"","test_series_name":"Science Test 1","title":"Science Test 1","test_code":"10th  aarambh test 1 25-26","test_type":"0","set_type":"0","total_marks":"70","start_date":"1746292980","end_date":"1771521660","lang_id":"1","type":"test","day_wise":"0","is_locked":"1","total_questions":"14","time_in_mins":"30","is_reattempt":"1765992000","report_id":"8692181","marks":"35","state":"1","correct_count":"7","incorrect_count":"3","lang_used":"1","submission_type":"0","result_status":"NA","description":"","solutions":"","question":"","answers":"","attempt":"0","answers_by_student":"","test_pattern":"0","folder_id":"0","l1_id":"8615","upload_allowed":"1","file_type":"t","is_test_purchased":"0","payload":{"topic_id":"35850","tile_id":"93496","tile_type":"test","revert_api":"0#0#0#0","course_id":"29246","day_wise":"0"}}]},"time":1760776779,"interval":1,"limit":180,"cd_time":17607759109966}